ShellArgParser/ShellArgParser.py
ShellArgParser/__init__.py
ShellArgParser/__main__.py
shellargparser-0.2.4.dist-info/licenses/LICENSE
shellargparser-0.2.4.dist-info/METADATA
shellargparser-0.2.4.dist-info/WHEEL
shellargparser-0.2.4.dist-info/entry_points.txt
shellargparser-0.2.4.dist-info/top_level.txt
shellargparser-0.2.4.dist-info/RECORD
