Metadata-Version: 2.4
Name: ShellArgParser
Version: 0.2.4
Summary: Simple tool to parse shell arguments using eval
Home-page: https://github.com/thiswillbeyourgithub/ShellArgParser
Keywords: shell,zsh,bash,arguments,args,kwargs,parser,tool
Classifier: Programming Language :: Python :: 3
Classifier: Operating System :: OS Independent
Requires-Python: >=3.9
License-File: LICENSE
Requires-Dist: fire>=0.5.0
Dynamic: classifier
Dynamic: description
Dynamic: description-content-type
Dynamic: home-page
Dynamic: keywords
Dynamic: license-file
Dynamic: requires-dist
Dynamic: requires-python
Dynamic: summary
